{
  "metadata" : {
    "identifier" : "https://truyenvnmoi.com/chu-thuat-hoi-chien",
    "title" : "Chú Thuật Hồi Chiến",
    "subtitle" : null,
    "author" : null,
    "narrator" : null,
    "language" : "vi",
    "description" : null,
    "publisher" : "N/A",
    "subject" : null,
    "modified" : null,
    "published" : "2023-04-29",
    "duration" : 0,
    "abridged" : false,
    "conformsTo" : "https://readium.org/webpub-manifest/profiles/divina",
    "numberOfPages" : 224,
    "readingProgression" : "ttb",
    "belongsTo" : null,
    "presentation" : {
      "fit" : "width",
      "overflow" : "scrolled",
      "continuous" : true
    },
    "@type" : null,
    "schema:license" : null
  },
  "links" : [ {
    "rel" : "self",
    "href" : "https://raw.githubusercontent.com/thuvienonline40/book_storage_collection/main/comic_manifest.json",
    "type" : "application/divina+json"
  } ],
  "readingOrder" : [ {
    "href" : "https://img.abctruyen.xyz/mt-sv-image/app/public/uploads/2021-02-12/703037/0.jpg",
    "type" : "image/jpeg",
    "bitrate" : 0,
    "duration" : 0,
    "title" : null,
    "properties" : null
  }, {
    "href" : "https://img.abctruyen.xyz/mt-sv-image/app/public/uploads/2021-02-12/703037/1.jpg",
    "type" : "image/jpeg",
    "bitrate" : 0,
    "duration" : 0,
    "title" : null,
    "properties" : null
  }, {
    "href" : "https://img.abctruyen.xyz/mt-sv-image/app/public/uploads/2021-02-12/703037/2.jpg",
    "type" : "image/jpeg",
    "bitrate" : 0,
    "duration" : 0,
    "title" : null,
    "properties" : null
  }, {
    "href" : "https://img.abctruyen.xyz/mt-sv-image/app/public/uploads/2021-02-12/703037/3.jpg",
    "type" : "image/jpeg",
    "bitrate" : 0,
    "duration" : 0,
    "title" : null,
    "properties" : null
  }, {
    "href" : "https://img.abctruyen.xyz/mt-sv-image/app/public/uploads/2021-02-12/703037/4.jpg",
    "type" : "image/jpeg",
    "bitrate" : 0,
    "duration" : 0,
    "title" : null,
    "properties" : null
  }, {
    "href" : "https://img.abctruyen.xyz/mt-sv-image/app/public/uploads/2021-02-12/703037/5.jpg",
    "type" : "image/jpeg",
    "bitrate" : 0,
    "duration" : 0,
    "title" : null,
    "properties" : null
  }, {
    "href" : "https://img.abctruyen.xyz/mt-sv-image/app/public/uploads/2021-02-12/703037/6.jpg",
    "type" : "image/jpeg",
    "bitrate" : 0,
    "duration" : 0,
    "title" : null,
    "properties" : null
  }, {
    "href" : "https://img.abctruyen.xyz/mt-sv-image/app/public/uploads/2021-02-12/703037/7.jpg",
    "type" : "image/jpeg",
    "bitrate" : 0,
    "duration" : 0,
    "title" : null,
    "properties" : null
  }, {
    "href" : "https://img.abctruyen.xyz/mt-sv-image/app/public/uploads/2021-02-12/703037/8.jpg",
    "type" : "image/jpeg",
    "bitrate" : 0,
    "duration" : 0,
    "title" : null,
    "properties" : null
  }, {
    "href" : "https://img.abctruyen.xyz/mt-sv-image/app/public/uploads/2021-02-12/703037/9.jpg",
    "type" : "image/jpeg",
    "bitrate" : 0,
    "duration" : 0,
    "title" : null,
    "properties" : null
  }, {
    "href" : "https://img.abctruyen.xyz/mt-sv-image/app/public/uploads/2021-02-12/703037/10.jpg",
    "type" : "image/jpeg",
    "bitrate" : 0,
    "duration" : 0,
    "title" : null,
    "properties" : null
  }, {
    "href" : "https://img.abctruyen.xyz/mt-sv-image/app/public/uploads/2021-02-12/703037/11.jpg",
    "type" : "image/jpeg",
    "bitrate" : 0,
    "duration" : 0,
    "title" : null,
    "properties" : null
  }, {
    "href" : "https://img.abctruyen.xyz/mt-sv-image/app/public/uploads/2021-02-12/703037/12.jpg",
    "type" : "image/jpeg",
    "bitrate" : 0,
    "duration" : 0,
    "title" : null,
    "properties" : null
  }, {
    "href" : "https://img.abctruyen.xyz/mt-sv-image/app/public/uploads/2021-02-12/703037/13.jpg",
    "type" : "image/jpeg",
    "bitrate" : 0,
    "duration" : 0,
    "title" : null,
    "properties" : null
  }, {
    "href" : "https://img.abctruyen.xyz/mt-sv-image/app/public/uploads/2021-02-12/703037/14.jpg",
    "type" : "image/jpeg",
    "bitrate" : 0,
    "duration" : 0,
    "title" : null,
    "properties" : null
  }, {
    "href" : "https://img.abctruyen.xyz/mt-sv-image/app/public/uploads/2021-02-12/703037/15.jpg",
    "type" : "image/jpeg",
    "bitrate" : 0,
    "duration" : 0,
    "title" : null,
    "properties" : null
  }, {
    "href" : "https://img.abctruyen.xyz/mt-sv-image/app/public/uploads/2021-02-12/703037/16.jpg",
    "type" : "image/jpeg",
    "bitrate" : 0,
    "duration" : 0,
    "title" : null,
    "properties" : null
  }, {
    "href" : "https://img.abctruyen.xyz/mt-sv-image/app/public/uploads/2021-02-12/703037/17.jpg",
    "type" : "image/jpeg",
    "bitrate" : 0,
    "duration" : 0,
    "title" : null,
    "properties" : null
  }, {
    "href" : "https://img.abctruyen.xyz/mt-sv-image/app/public/uploads/2021-02-12/703037/18.jpg",
    "type" : "image/jpeg",
    "bitrate" : 0,
    "duration" : 0,
    "title" : null,
    "properties" : null
  }, {
    "href" : "https://img.abctruyen.xyz/mt-sv-image/app/public/uploads/2021-02-12/703037/19.jpg",
    "type" : "image/jpeg",
    "bitrate" : 0,
    "duration" : 0,
    "title" : null,
    "properties" : null
  }, {
    "href" : "https://img.abctruyen.xyz/mt-sv-image/app/public/uploads/2021-02-12/703037/20.jpg",
    "type" : "image/jpeg",
    "bitrate" : 0,
    "duration" : 0,
    "title" : null,
    "properties" : null
  }, {
    "href" : "https://img.abctruyen.xyz/mt-sv-image/app/public/uploads/2021-02-12/703037/21.jpg",
    "type" : "image/jpeg",
    "bitrate" : 0,
    "duration" : 0,
    "title" : null,
    "properties" : null
  }, {
    "href" : "https://img.abctruyen.xyz/mt-sv-image/app/public/uploads/2021-02-12/703037/22.jpg",
    "type" : "image/jpeg",
    "bitrate" : 0,
    "duration" : 0,
    "title" : null,
    "properties" : null
  }, {
    "href" : "https://img.abctruyen.xyz/mt-sv-image/app/public/uploads/2021-02-12/703037/23.jpg",
    "type" : "image/jpeg",
    "bitrate" : 0,
    "duration" : 0,
    "title" : null,
    "properties" : null
  }, {
    "href" : "https://i2.wp.com/truyenvnhot.net/wp-content/uploads/2022/12/truyenvn-gg-banner.jpg",
    "type" : "image/jpeg",
    "bitrate" : 0,
    "duration" : 0,
    "title" : null,
    "properties" : null
  } ],
  "toc" : null,
  "@context" : "https://readium.org/webpub-manifest/context.jsonld"
}