{
  "metadata" : {
    "identifier" : "https://www.nettruyento.com/truyen-tranh/hoi-phap-su-noi-tieng-91701",
    "title" : "Hội Pháp Sư Nổi Tiếng - Chapter 72",
    "subtitle" : null,
    "author" : null,
    "narrator" : null,
    "language" : "vi",
    "description" : null,
    "publisher" : "N/A",
    "subject" : null,
    "modified" : null,
    "published" : "2023-06-09",
    "duration" : 0,
    "abridged" : false,
    "conformsTo" : "https://readium.org/webpub-manifest/profiles/divina",
    "numberOfPages" : 560,
    "readingProgression" : "ttb",
    "belongsTo" : null,
    "presentation" : {
      "fit" : "width",
      "overflow" : "scrolled",
      "continuous" : true
    },
    "@type" : null,
    "schema:license" : null
  },
  "links" : [ {
    "rel" : "self",
    "href" : "https://raw.githubusercontent.com/thuvienonline40/book_storage_collection/main/comic_manifest.json",
    "type" : "application/divina+json"
  } ],
  "readingOrder" : [ {
    "href" : "https://bitbucket.org/wp-tsvhcomic24/comic_storage22/raw/master/IMAGE/IMAGE_32fd53686848c43580f2e351182d0ad8_a8ed87243785bfe6ea1a75b948a62126_0d1c3a74e2901480c4d88f24d448349b.jpg",
    "type" : "image/jpeg",
    "bitrate" : 0,
    "duration" : 0,
    "title" : null,
    "properties" : null,
    "alternate" : [ {
      "href" : "https://i441.ntcdntempv26.com/data/images/9170/172336/001.jpg?data=net",
      "type" : "image/jpeg",
      "bitrate" : 0,
      "duration" : 0,
      "title" : null,
      "properties" : null,
      "alternate" : null
    } ]
  }, {
    "href" : "https://bitbucket.org/wp-tsvhcomic24/comic_storage22/raw/master/IMAGE/IMAGE_32fd53686848c43580f2e351182d0ad8_a8ed87243785bfe6ea1a75b948a62126_4e6f313475bd0b601c62b1a909405c94.jpg",
    "type" : "image/jpeg",
    "bitrate" : 0,
    "duration" : 0,
    "title" : null,
    "properties" : null,
    "alternate" : [ {
      "href" : "https://i441.ntcdntempv26.com/data/images/9170/172336/002.jpg?data=net",
      "type" : "image/jpeg",
      "bitrate" : 0,
      "duration" : 0,
      "title" : null,
      "properties" : null,
      "alternate" : null
    } ]
  }, {
    "href" : "https://bitbucket.org/wp-tsvhcomic24/comic_storage22/raw/master/IMAGE/IMAGE_32fd53686848c43580f2e351182d0ad8_a8ed87243785bfe6ea1a75b948a62126_bf1e7bf82de91035fc1fee6afcfafef0.jpg",
    "type" : "image/jpeg",
    "bitrate" : 0,
    "duration" : 0,
    "title" : null,
    "properties" : null,
    "alternate" : [ {
      "href" : "https://i441.ntcdntempv26.com/data/images/9170/172336/003.jpg?data=net",
      "type" : "image/jpeg",
      "bitrate" : 0,
      "duration" : 0,
      "title" : null,
      "properties" : null,
      "alternate" : null
    } ]
  }, {
    "href" : "https://bitbucket.org/wp-tsvhcomic24/comic_storage22/raw/master/IMAGE/IMAGE_32fd53686848c43580f2e351182d0ad8_a8ed87243785bfe6ea1a75b948a62126_caef837053cd287677908a4939145a00.jpg",
    "type" : "image/jpeg",
    "bitrate" : 0,
    "duration" : 0,
    "title" : null,
    "properties" : null,
    "alternate" : [ {
      "href" : "https://i441.ntcdntempv26.com/data/images/9170/172336/004.jpg?data=net",
      "type" : "image/jpeg",
      "bitrate" : 0,
      "duration" : 0,
      "title" : null,
      "properties" : null,
      "alternate" : null
    } ]
  }, {
    "href" : "https://bitbucket.org/wp-tsvhcomic24/comic_storage22/raw/master/IMAGE/IMAGE_32fd53686848c43580f2e351182d0ad8_a8ed87243785bfe6ea1a75b948a62126_402589dd7120e4555aa9bd04887f34fb.jpg",
    "type" : "image/jpeg",
    "bitrate" : 0,
    "duration" : 0,
    "title" : null,
    "properties" : null,
    "alternate" : [ {
      "href" : "https://i441.ntcdntempv26.com/data/images/9170/172336/005.jpg?data=net",
      "type" : "image/jpeg",
      "bitrate" : 0,
      "duration" : 0,
      "title" : null,
      "properties" : null,
      "alternate" : null
    } ]
  }, {
    "href" : "https://bitbucket.org/wp-tsvhcomic24/comic_storage22/raw/master/IMAGE/IMAGE_32fd53686848c43580f2e351182d0ad8_a8ed87243785bfe6ea1a75b948a62126_1050771083b19aac05011e2614e84cf5.jpg",
    "type" : "image/jpeg",
    "bitrate" : 0,
    "duration" : 0,
    "title" : null,
    "properties" : null,
    "alternate" : [ {
      "href" : "https://i441.ntcdntempv26.com/data/images/9170/172336/006.jpg?data=net",
      "type" : "image/jpeg",
      "bitrate" : 0,
      "duration" : 0,
      "title" : null,
      "properties" : null,
      "alternate" : null
    } ]
  }, {
    "href" : "https://bitbucket.org/wp-tsvhcomic24/comic_storage22/raw/master/IMAGE/IMAGE_32fd53686848c43580f2e351182d0ad8_a8ed87243785bfe6ea1a75b948a62126_ae3c87ae5333edfdd5e04bb5eca39c5e.jpg",
    "type" : "image/jpeg",
    "bitrate" : 0,
    "duration" : 0,
    "title" : null,
    "properties" : null,
    "alternate" : [ {
      "href" : "https://i441.ntcdntempv26.com/data/images/9170/172336/007.jpg?data=net",
      "type" : "image/jpeg",
      "bitrate" : 0,
      "duration" : 0,
      "title" : null,
      "properties" : null,
      "alternate" : null
    } ]
  }, {
    "href" : "https://bitbucket.org/wp-tsvhcomic24/comic_storage22/raw/master/IMAGE/IMAGE_32fd53686848c43580f2e351182d0ad8_a8ed87243785bfe6ea1a75b948a62126_8ef445b9875dff8d42f62f1c5059d1e3.jpg",
    "type" : "image/jpeg",
    "bitrate" : 0,
    "duration" : 0,
    "title" : null,
    "properties" : null,
    "alternate" : [ {
      "href" : "https://i441.ntcdntempv26.com/data/images/9170/172336/008.jpg?data=net",
      "type" : "image/jpeg",
      "bitrate" : 0,
      "duration" : 0,
      "title" : null,
      "properties" : null,
      "alternate" : null
    } ]
  }, {
    "href" : "https://bitbucket.org/wp-tsvhcomic24/comic_storage22/raw/master/IMAGE/IMAGE_32fd53686848c43580f2e351182d0ad8_a8ed87243785bfe6ea1a75b948a62126_4e6bb00defa642a29ee2dff6d8daa5b8.jpg",
    "type" : "image/jpeg",
    "bitrate" : 0,
    "duration" : 0,
    "title" : null,
    "properties" : null,
    "alternate" : [ {
      "href" : "https://i441.ntcdntempv26.com/data/images/9170/172336/009.jpg?data=net",
      "type" : "image/jpeg",
      "bitrate" : 0,
      "duration" : 0,
      "title" : null,
      "properties" : null,
      "alternate" : null
    } ]
  }, {
    "href" : "https://bitbucket.org/wp-tsvhcomic24/comic_storage22/raw/master/IMAGE/IMAGE_32fd53686848c43580f2e351182d0ad8_a8ed87243785bfe6ea1a75b948a62126_94ab81a97af4975b785426a2a2daf3ef.jpg",
    "type" : "image/jpeg",
    "bitrate" : 0,
    "duration" : 0,
    "title" : null,
    "properties" : null,
    "alternate" : [ {
      "href" : "https://i441.ntcdntempv26.com/data/images/9170/172336/010.jpg?data=net",
      "type" : "image/jpeg",
      "bitrate" : 0,
      "duration" : 0,
      "title" : null,
      "properties" : null,
      "alternate" : null
    } ]
  }, {
    "href" : "https://bitbucket.org/wp-tsvhcomic24/comic_storage22/raw/master/IMAGE/IMAGE_32fd53686848c43580f2e351182d0ad8_a8ed87243785bfe6ea1a75b948a62126_3331d094243b9a5bd8dbe012880aadda.jpg",
    "type" : "image/jpeg",
    "bitrate" : 0,
    "duration" : 0,
    "title" : null,
    "properties" : null,
    "alternate" : [ {
      "href" : "https://i441.ntcdntempv26.com/data/images/9170/172336/011.jpg?data=net",
      "type" : "image/jpeg",
      "bitrate" : 0,
      "duration" : 0,
      "title" : null,
      "properties" : null,
      "alternate" : null
    } ]
  }, {
    "href" : "https://bitbucket.org/wp-tsvhcomic24/comic_storage22/raw/master/IMAGE/IMAGE_32fd53686848c43580f2e351182d0ad8_a8ed87243785bfe6ea1a75b948a62126_76ec420bcd59ea98a9bd14ef4c68cb56.jpg",
    "type" : "image/jpeg",
    "bitrate" : 0,
    "duration" : 0,
    "title" : null,
    "properties" : null,
    "alternate" : [ {
      "href" : "https://i441.ntcdntempv26.com/data/images/9170/172336/012.jpg?data=net",
      "type" : "image/jpeg",
      "bitrate" : 0,
      "duration" : 0,
      "title" : null,
      "properties" : null,
      "alternate" : null
    } ]
  }, {
    "href" : "https://bitbucket.org/wp-tsvhcomic24/comic_storage22/raw/master/IMAGE/IMAGE_32fd53686848c43580f2e351182d0ad8_a8ed87243785bfe6ea1a75b948a62126_3f1c4dc78589241b426d8bf6b0d1849b.jpg",
    "type" : "image/jpeg",
    "bitrate" : 0,
    "duration" : 0,
    "title" : null,
    "properties" : null,
    "alternate" : [ {
      "href" : "https://i441.ntcdntempv26.com/data/images/9170/172336/013.jpg?data=net",
      "type" : "image/jpeg",
      "bitrate" : 0,
      "duration" : 0,
      "title" : null,
      "properties" : null,
      "alternate" : null
    } ]
  }, {
    "href" : "https://bitbucket.org/wp-tsvhcomic24/comic_storage22/raw/master/IMAGE/IMAGE_32fd53686848c43580f2e351182d0ad8_a8ed87243785bfe6ea1a75b948a62126_e46d002972b11cc81c002df10ac2c7af.jpg",
    "type" : "image/jpeg",
    "bitrate" : 0,
    "duration" : 0,
    "title" : null,
    "properties" : null,
    "alternate" : [ {
      "href" : "https://i441.ntcdntempv26.com/data/images/9170/172336/014.jpg?data=net",
      "type" : "image/jpeg",
      "bitrate" : 0,
      "duration" : 0,
      "title" : null,
      "properties" : null,
      "alternate" : null
    } ]
  }, {
    "href" : "https://bitbucket.org/wp-tsvhcomic24/comic_storage22/raw/master/IMAGE/IMAGE_32fd53686848c43580f2e351182d0ad8_a8ed87243785bfe6ea1a75b948a62126_7ec0277803eff96ef5951b722560c18f.jpg",
    "type" : "image/jpeg",
    "bitrate" : 0,
    "duration" : 0,
    "title" : null,
    "properties" : null,
    "alternate" : [ {
      "href" : "https://i441.ntcdntempv26.com/data/images/9170/172336/015.jpg?data=net",
      "type" : "image/jpeg",
      "bitrate" : 0,
      "duration" : 0,
      "title" : null,
      "properties" : null,
      "alternate" : null
    } ]
  }, {
    "href" : "https://bitbucket.org/wp-tsvhcomic24/comic_storage22/raw/master/IMAGE/IMAGE_32fd53686848c43580f2e351182d0ad8_a8ed87243785bfe6ea1a75b948a62126_b8217709199c38dba6038a8491651796.jpg",
    "type" : "image/jpeg",
    "bitrate" : 0,
    "duration" : 0,
    "title" : null,
    "properties" : null,
    "alternate" : [ {
      "href" : "https://i441.ntcdntempv26.com/data/images/9170/172336/016.jpg?data=net",
      "type" : "image/jpeg",
      "bitrate" : 0,
      "duration" : 0,
      "title" : null,
      "properties" : null,
      "alternate" : null
    } ]
  }, {
    "href" : "https://bitbucket.org/wp-tsvhcomic24/comic_storage22/raw/master/IMAGE/IMAGE_32fd53686848c43580f2e351182d0ad8_a8ed87243785bfe6ea1a75b948a62126_52c8ce13749b4e1c78cb9906d159a756.jpg",
    "type" : "image/jpeg",
    "bitrate" : 0,
    "duration" : 0,
    "title" : null,
    "properties" : null,
    "alternate" : [ {
      "href" : "https://i441.ntcdntempv26.com/data/images/9170/172336/017.jpg?data=net",
      "type" : "image/jpeg",
      "bitrate" : 0,
      "duration" : 0,
      "title" : null,
      "properties" : null,
      "alternate" : null
    } ]
  }, {
    "href" : "https://bitbucket.org/wp-tsvhcomic24/comic_storage22/raw/master/IMAGE/IMAGE_32fd53686848c43580f2e351182d0ad8_a8ed87243785bfe6ea1a75b948a62126_2995645751c712c6f73f1b401e06a3b4.jpg",
    "type" : "image/jpeg",
    "bitrate" : 0,
    "duration" : 0,
    "title" : null,
    "properties" : null,
    "alternate" : [ {
      "href" : "https://i441.ntcdntempv26.com/data/images/9170/172336/018.jpg?data=net",
      "type" : "image/jpeg",
      "bitrate" : 0,
      "duration" : 0,
      "title" : null,
      "properties" : null,
      "alternate" : null
    } ]
  }, {
    "href" : "https://bitbucket.org/wp-tsvhcomic24/comic_storage22/raw/master/IMAGE/IMAGE_32fd53686848c43580f2e351182d0ad8_a8ed87243785bfe6ea1a75b948a62126_e33c01f12baf9a4182300db081934ad2.jpg",
    "type" : "image/jpeg",
    "bitrate" : 0,
    "duration" : 0,
    "title" : null,
    "properties" : null,
    "alternate" : [ {
      "href" : "https://i441.ntcdntempv26.com/data/images/9170/172336/019.jpg?data=net",
      "type" : "image/jpeg",
      "bitrate" : 0,
      "duration" : 0,
      "title" : null,
      "properties" : null,
      "alternate" : null
    } ]
  }, {
    "href" : "https://bitbucket.org/wp-tsvhcomic24/comic_storage22/raw/master/IMAGE/IMAGE_32fd53686848c43580f2e351182d0ad8_a8ed87243785bfe6ea1a75b948a62126_9b16c6ec82902a8d997dac18ef31373a.jpg",
    "type" : "image/jpeg",
    "bitrate" : 0,
    "duration" : 0,
    "title" : null,
    "properties" : null,
    "alternate" : [ {
      "href" : "https://i441.ntcdntempv26.com/data/images/9170/172336/020.jpg?data=net",
      "type" : "image/jpeg",
      "bitrate" : 0,
      "duration" : 0,
      "title" : null,
      "properties" : null,
      "alternate" : null
    } ]
  }, {
    "href" : "https://bitbucket.org/wp-tsvhcomic24/comic_storage22/raw/master/IMAGE/IMAGE_32fd53686848c43580f2e351182d0ad8_a8ed87243785bfe6ea1a75b948a62126_d7d219833e7a8609fc9ec0ec05280ace.jpg",
    "type" : "image/jpeg",
    "bitrate" : 0,
    "duration" : 0,
    "title" : null,
    "properties" : null,
    "alternate" : [ {
      "href" : "https://i441.ntcdntempv26.com/data/images/9170/172336/021.jpg?data=net",
      "type" : "image/jpeg",
      "bitrate" : 0,
      "duration" : 0,
      "title" : null,
      "properties" : null,
      "alternate" : null
    } ]
  }, {
    "href" : "https://bitbucket.org/wp-tsvhcomic24/comic_storage22/raw/master/IMAGE/IMAGE_32fd53686848c43580f2e351182d0ad8_a8ed87243785bfe6ea1a75b948a62126_b87134869867f39ed4ca800b12a738f1.jpg",
    "type" : "image/jpeg",
    "bitrate" : 0,
    "duration" : 0,
    "title" : null,
    "properties" : null,
    "alternate" : [ {
      "href" : "https://i441.ntcdntempv26.com/data/images/9170/172336/022.jpg?data=net",
      "type" : "image/jpeg",
      "bitrate" : 0,
      "duration" : 0,
      "title" : null,
      "properties" : null,
      "alternate" : null
    } ]
  }, {
    "href" : "https://bitbucket.org/wp-tsvhcomic24/comic_storage22/raw/master/IMAGE/IMAGE_32fd53686848c43580f2e351182d0ad8_a8ed87243785bfe6ea1a75b948a62126_f298f6b83896a6352b351a349f2df041.jpg",
    "type" : "image/jpeg",
    "bitrate" : 0,
    "duration" : 0,
    "title" : null,
    "properties" : null,
    "alternate" : [ {
      "href" : "https://i441.ntcdntempv26.com/data/images/9170/172336/023.jpg?data=net",
      "type" : "image/jpeg",
      "bitrate" : 0,
      "duration" : 0,
      "title" : null,
      "properties" : null,
      "alternate" : null
    } ]
  }, {
    "href" : "https://bitbucket.org/wp-tsvhcomic24/comic_storage22/raw/master/IMAGE/IMAGE_32fd53686848c43580f2e351182d0ad8_a8ed87243785bfe6ea1a75b948a62126_1e5fed8edacacfbd1d6c58eba35c1800.jpg",
    "type" : "image/jpeg",
    "bitrate" : 0,
    "duration" : 0,
    "title" : null,
    "properties" : null,
    "alternate" : [ {
      "href" : "https://i441.ntcdntempv26.com/data/images/9170/172336/024.jpg?data=net",
      "type" : "image/jpeg",
      "bitrate" : 0,
      "duration" : 0,
      "title" : null,
      "properties" : null,
      "alternate" : null
    } ]
  } ],
  "toc" : null,
  "@context" : "https://readium.org/webpub-manifest/context.jsonld"
}