{
  "metadata" : {
    "identifier" : "https://www.nettruyento.com/truyen-tranh/hoi-phap-su-noi-tieng-91701",
    "title" : "Hội Pháp Sư Nổi Tiếng - Chapter 496",
    "subtitle" : null,
    "author" : null,
    "narrator" : null,
    "language" : "vi",
    "description" : null,
    "publisher" : "N/A",
    "subject" : null,
    "modified" : null,
    "published" : "2023-06-09",
    "duration" : 0,
    "abridged" : false,
    "conformsTo" : "https://readium.org/webpub-manifest/profiles/divina",
    "numberOfPages" : 560,
    "readingProgression" : "ttb",
    "belongsTo" : null,
    "presentation" : {
      "fit" : "width",
      "overflow" : "scrolled",
      "continuous" : true
    },
    "@type" : null,
    "schema:license" : null
  },
  "links" : [ {
    "rel" : "self",
    "href" : "https://raw.githubusercontent.com/thuvienonline40/book_storage_collection/main/comic_manifest.json",
    "type" : "application/divina+json"
  } ],
  "readingOrder" : [ {
    "href" : "https://raw.githubusercontent.com/duyhuynh652018/comic_storage9/main/IMAGE/IMAGE_32fd53686848c43580f2e351182d0ad8_0174d13e5dbeef7be19e7c3f7fa30fdd_092cc15f4eb89a1fee0961e1c599bb1c.jpg",
    "type" : "image/jpeg",
    "bitrate" : 0,
    "duration" : 0,
    "title" : null,
    "properties" : null,
    "alternate" : [ {
      "href" : "https://i115.ntcdntempv3.com/data/images/9170/275777/001-fix.jpg?data=net",
      "type" : "image/jpeg",
      "bitrate" : 0,
      "duration" : 0,
      "title" : null,
      "properties" : null,
      "alternate" : null
    } ]
  }, {
    "href" : "https://raw.githubusercontent.com/duyhuynh652018/comic_storage9/main/IMAGE/IMAGE_32fd53686848c43580f2e351182d0ad8_0174d13e5dbeef7be19e7c3f7fa30fdd_d6e90322f389062a28dbe14b87fc2e0f.jpg",
    "type" : "image/jpeg",
    "bitrate" : 0,
    "duration" : 0,
    "title" : null,
    "properties" : null,
    "alternate" : [ {
      "href" : "https://i115.ntcdntempv3.com/data/images/9170/275777/002-fix.jpg?data=net",
      "type" : "image/jpeg",
      "bitrate" : 0,
      "duration" : 0,
      "title" : null,
      "properties" : null,
      "alternate" : null
    } ]
  }, {
    "href" : "https://raw.githubusercontent.com/duyhuynh652018/comic_storage9/main/IMAGE/IMAGE_32fd53686848c43580f2e351182d0ad8_0174d13e5dbeef7be19e7c3f7fa30fdd_4b45c51d3f77a27ee1209a50a267294d.jpg",
    "type" : "image/jpeg",
    "bitrate" : 0,
    "duration" : 0,
    "title" : null,
    "properties" : null,
    "alternate" : [ {
      "href" : "https://i115.ntcdntempv3.com/data/images/9170/275777/003-fix.jpg?data=net",
      "type" : "image/jpeg",
      "bitrate" : 0,
      "duration" : 0,
      "title" : null,
      "properties" : null,
      "alternate" : null
    } ]
  }, {
    "href" : "https://raw.githubusercontent.com/duyhuynh652018/comic_storage9/main/IMAGE/IMAGE_32fd53686848c43580f2e351182d0ad8_0174d13e5dbeef7be19e7c3f7fa30fdd_203219e075f2e8918111bffcc987139f.jpg",
    "type" : "image/jpeg",
    "bitrate" : 0,
    "duration" : 0,
    "title" : null,
    "properties" : null,
    "alternate" : [ {
      "href" : "https://i115.ntcdntempv3.com/data/images/9170/275777/004-fix.jpg?data=net",
      "type" : "image/jpeg",
      "bitrate" : 0,
      "duration" : 0,
      "title" : null,
      "properties" : null,
      "alternate" : null
    } ]
  }, {
    "href" : "https://raw.githubusercontent.com/duyhuynh652018/comic_storage9/main/IMAGE/IMAGE_32fd53686848c43580f2e351182d0ad8_0174d13e5dbeef7be19e7c3f7fa30fdd_ee7275ebede1d34680d98b4ab602e43d.jpg",
    "type" : "image/jpeg",
    "bitrate" : 0,
    "duration" : 0,
    "title" : null,
    "properties" : null,
    "alternate" : [ {
      "href" : "https://i115.ntcdntempv3.com/data/images/9170/275777/005-fix.jpg?data=net",
      "type" : "image/jpeg",
      "bitrate" : 0,
      "duration" : 0,
      "title" : null,
      "properties" : null,
      "alternate" : null
    } ]
  }, {
    "href" : "https://raw.githubusercontent.com/duyhuynh652018/comic_storage9/main/IMAGE/IMAGE_32fd53686848c43580f2e351182d0ad8_0174d13e5dbeef7be19e7c3f7fa30fdd_d6bca5c32bc514e13a3a74a6a6e09b72.jpg",
    "type" : "image/jpeg",
    "bitrate" : 0,
    "duration" : 0,
    "title" : null,
    "properties" : null,
    "alternate" : [ {
      "href" : "https://i115.ntcdntempv3.com/data/images/9170/275777/006-fix.jpg?data=net",
      "type" : "image/jpeg",
      "bitrate" : 0,
      "duration" : 0,
      "title" : null,
      "properties" : null,
      "alternate" : null
    } ]
  }, {
    "href" : "https://raw.githubusercontent.com/duyhuynh652018/comic_storage9/main/IMAGE/IMAGE_32fd53686848c43580f2e351182d0ad8_0174d13e5dbeef7be19e7c3f7fa30fdd_01095a55ab8689d3248a663a9f394b3a.jpg",
    "type" : "image/jpeg",
    "bitrate" : 0,
    "duration" : 0,
    "title" : null,
    "properties" : null,
    "alternate" : [ {
      "href" : "https://i115.ntcdntempv3.com/data/images/9170/275777/007-fix.jpg?data=net",
      "type" : "image/jpeg",
      "bitrate" : 0,
      "duration" : 0,
      "title" : null,
      "properties" : null,
      "alternate" : null
    } ]
  }, {
    "href" : "https://raw.githubusercontent.com/duyhuynh652018/comic_storage9/main/IMAGE/IMAGE_32fd53686848c43580f2e351182d0ad8_0174d13e5dbeef7be19e7c3f7fa30fdd_e5acb15673a84c5326bfa1f8c74e015f.jpg",
    "type" : "image/jpeg",
    "bitrate" : 0,
    "duration" : 0,
    "title" : null,
    "properties" : null,
    "alternate" : [ {
      "href" : "https://i115.ntcdntempv3.com/data/images/9170/275777/008-fix.jpg?data=net",
      "type" : "image/jpeg",
      "bitrate" : 0,
      "duration" : 0,
      "title" : null,
      "properties" : null,
      "alternate" : null
    } ]
  }, {
    "href" : "https://raw.githubusercontent.com/duyhuynh652018/comic_storage9/main/IMAGE/IMAGE_32fd53686848c43580f2e351182d0ad8_0174d13e5dbeef7be19e7c3f7fa30fdd_bfc9d6c0972fef329a0d0d04d18baf57.jpg",
    "type" : "image/jpeg",
    "bitrate" : 0,
    "duration" : 0,
    "title" : null,
    "properties" : null,
    "alternate" : [ {
      "href" : "https://i115.ntcdntempv3.com/data/images/9170/275777/009-fix.jpg?data=net",
      "type" : "image/jpeg",
      "bitrate" : 0,
      "duration" : 0,
      "title" : null,
      "properties" : null,
      "alternate" : null
    } ]
  }, {
    "href" : "https://raw.githubusercontent.com/duyhuynh652018/comic_storage9/main/IMAGE/IMAGE_32fd53686848c43580f2e351182d0ad8_0174d13e5dbeef7be19e7c3f7fa30fdd_95c014f02f17afe469db70142b974195.jpg",
    "type" : "image/jpeg",
    "bitrate" : 0,
    "duration" : 0,
    "title" : null,
    "properties" : null,
    "alternate" : [ {
      "href" : "https://i115.ntcdntempv3.com/data/images/9170/275777/010-fix.jpg?data=net",
      "type" : "image/jpeg",
      "bitrate" : 0,
      "duration" : 0,
      "title" : null,
      "properties" : null,
      "alternate" : null
    } ]
  }, {
    "href" : "https://raw.githubusercontent.com/duyhuynh652018/comic_storage9/main/IMAGE/IMAGE_32fd53686848c43580f2e351182d0ad8_0174d13e5dbeef7be19e7c3f7fa30fdd_a9e71464bd796eb7ae7144671f9efe0a.jpg",
    "type" : "image/jpeg",
    "bitrate" : 0,
    "duration" : 0,
    "title" : null,
    "properties" : null,
    "alternate" : [ {
      "href" : "https://i115.ntcdntempv3.com/data/images/9170/275777/011-fix.jpg?data=net",
      "type" : "image/jpeg",
      "bitrate" : 0,
      "duration" : 0,
      "title" : null,
      "properties" : null,
      "alternate" : null
    } ]
  }, {
    "href" : "https://raw.githubusercontent.com/duyhuynh652018/comic_storage9/main/IMAGE/IMAGE_32fd53686848c43580f2e351182d0ad8_0174d13e5dbeef7be19e7c3f7fa30fdd_75034a876b82e50bca8b0b3bbc625a35.jpg",
    "type" : "image/jpeg",
    "bitrate" : 0,
    "duration" : 0,
    "title" : null,
    "properties" : null,
    "alternate" : [ {
      "href" : "https://i115.ntcdntempv3.com/data/images/9170/275777/012-fix.jpg?data=net",
      "type" : "image/jpeg",
      "bitrate" : 0,
      "duration" : 0,
      "title" : null,
      "properties" : null,
      "alternate" : null
    } ]
  }, {
    "href" : "https://raw.githubusercontent.com/duyhuynh652018/comic_storage9/main/IMAGE/IMAGE_32fd53686848c43580f2e351182d0ad8_0174d13e5dbeef7be19e7c3f7fa30fdd_7000e5a30892114a743158cb977c8325.jpg",
    "type" : "image/jpeg",
    "bitrate" : 0,
    "duration" : 0,
    "title" : null,
    "properties" : null,
    "alternate" : [ {
      "href" : "https://i115.ntcdntempv3.com/data/images/9170/275777/013-fix.jpg?data=net",
      "type" : "image/jpeg",
      "bitrate" : 0,
      "duration" : 0,
      "title" : null,
      "properties" : null,
      "alternate" : null
    } ]
  }, {
    "href" : "https://raw.githubusercontent.com/duyhuynh652018/comic_storage9/main/IMAGE/IMAGE_32fd53686848c43580f2e351182d0ad8_0174d13e5dbeef7be19e7c3f7fa30fdd_ee3251fea8fbbc01b7ba883c4771fe24.jpg",
    "type" : "image/jpeg",
    "bitrate" : 0,
    "duration" : 0,
    "title" : null,
    "properties" : null,
    "alternate" : [ {
      "href" : "https://i115.ntcdntempv3.com/data/images/9170/275777/014-fix.jpg?data=net",
      "type" : "image/jpeg",
      "bitrate" : 0,
      "duration" : 0,
      "title" : null,
      "properties" : null,
      "alternate" : null
    } ]
  }, {
    "href" : "https://raw.githubusercontent.com/duyhuynh652018/comic_storage9/main/IMAGE/IMAGE_32fd53686848c43580f2e351182d0ad8_0174d13e5dbeef7be19e7c3f7fa30fdd_8798051f8c8651e4cf455b093e012132.jpg",
    "type" : "image/jpeg",
    "bitrate" : 0,
    "duration" : 0,
    "title" : null,
    "properties" : null,
    "alternate" : [ {
      "href" : "https://i115.ntcdntempv3.com/data/images/9170/275777/015-fix.jpg?data=net",
      "type" : "image/jpeg",
      "bitrate" : 0,
      "duration" : 0,
      "title" : null,
      "properties" : null,
      "alternate" : null
    } ]
  }, {
    "href" : "https://raw.githubusercontent.com/duyhuynh652018/comic_storage9/main/IMAGE/IMAGE_32fd53686848c43580f2e351182d0ad8_0174d13e5dbeef7be19e7c3f7fa30fdd_7bf8b3f38a92cbd9022b4a6e5a7cd573.jpg",
    "type" : "image/jpeg",
    "bitrate" : 0,
    "duration" : 0,
    "title" : null,
    "properties" : null,
    "alternate" : [ {
      "href" : "https://i115.ntcdntempv3.com/data/images/9170/275777/016-fix.jpg?data=net",
      "type" : "image/jpeg",
      "bitrate" : 0,
      "duration" : 0,
      "title" : null,
      "properties" : null,
      "alternate" : null
    } ]
  }, {
    "href" : "https://raw.githubusercontent.com/duyhuynh652018/comic_storage9/main/IMAGE/IMAGE_32fd53686848c43580f2e351182d0ad8_0174d13e5dbeef7be19e7c3f7fa30fdd_1ac6e59ca67f072c32d4656fde8391c5.jpg",
    "type" : "image/jpeg",
    "bitrate" : 0,
    "duration" : 0,
    "title" : null,
    "properties" : null,
    "alternate" : [ {
      "href" : "https://i115.ntcdntempv3.com/data/images/9170/275777/017-fix.jpg?data=net",
      "type" : "image/jpeg",
      "bitrate" : 0,
      "duration" : 0,
      "title" : null,
      "properties" : null,
      "alternate" : null
    } ]
  }, {
    "href" : "https://raw.githubusercontent.com/duyhuynh652018/comic_storage9/main/IMAGE/IMAGE_32fd53686848c43580f2e351182d0ad8_0174d13e5dbeef7be19e7c3f7fa30fdd_384dd9c6a4ee2234534b80953ccde016.jpg",
    "type" : "image/jpeg",
    "bitrate" : 0,
    "duration" : 0,
    "title" : null,
    "properties" : null,
    "alternate" : [ {
      "href" : "https://i115.ntcdntempv3.com/data/images/9170/275777/018-fix.jpg?data=net",
      "type" : "image/jpeg",
      "bitrate" : 0,
      "duration" : 0,
      "title" : null,
      "properties" : null,
      "alternate" : null
    } ]
  }, {
    "href" : "https://raw.githubusercontent.com/duyhuynh652018/comic_storage9/main/IMAGE/IMAGE_32fd53686848c43580f2e351182d0ad8_0174d13e5dbeef7be19e7c3f7fa30fdd_d3d570588e4a347b9f719a12907e3006.jpg",
    "type" : "image/jpeg",
    "bitrate" : 0,
    "duration" : 0,
    "title" : null,
    "properties" : null,
    "alternate" : [ {
      "href" : "https://i115.ntcdntempv3.com/data/images/9170/275777/019-fix.jpg?data=net",
      "type" : "image/jpeg",
      "bitrate" : 0,
      "duration" : 0,
      "title" : null,
      "properties" : null,
      "alternate" : null
    } ]
  }, {
    "href" : "https://raw.githubusercontent.com/duyhuynh652018/comic_storage9/main/IMAGE/IMAGE_32fd53686848c43580f2e351182d0ad8_0174d13e5dbeef7be19e7c3f7fa30fdd_0d17de385927d2a7399aecb57369ec93.jpg",
    "type" : "image/jpeg",
    "bitrate" : 0,
    "duration" : 0,
    "title" : null,
    "properties" : null,
    "alternate" : [ {
      "href" : "https://i115.ntcdntempv3.com/data/images/9170/275777/020-fix.jpg?data=net",
      "type" : "image/jpeg",
      "bitrate" : 0,
      "duration" : 0,
      "title" : null,
      "properties" : null,
      "alternate" : null
    } ]
  }, {
    "href" : "https://raw.githubusercontent.com/duyhuynh652018/comic_storage9/main/IMAGE/IMAGE_32fd53686848c43580f2e351182d0ad8_0174d13e5dbeef7be19e7c3f7fa30fdd_fd5f7dfcf283fe3d0be3f398231c4b1d.jpg",
    "type" : "image/jpeg",
    "bitrate" : 0,
    "duration" : 0,
    "title" : null,
    "properties" : null,
    "alternate" : [ {
      "href" : "https://i115.ntcdntempv3.com/data/images/9170/275777/021-fix.jpg?data=net",
      "type" : "image/jpeg",
      "bitrate" : 0,
      "duration" : 0,
      "title" : null,
      "properties" : null,
      "alternate" : null
    } ]
  }, {
    "href" : "https://raw.githubusercontent.com/duyhuynh652018/comic_storage9/main/IMAGE/IMAGE_32fd53686848c43580f2e351182d0ad8_0174d13e5dbeef7be19e7c3f7fa30fdd_409fe746df9491892b276af5d512e9f2.jpg",
    "type" : "image/jpeg",
    "bitrate" : 0,
    "duration" : 0,
    "title" : null,
    "properties" : null,
    "alternate" : [ {
      "href" : "https://i115.ntcdntempv3.com/data/images/9170/275777/022-fix.jpg?data=net",
      "type" : "image/jpeg",
      "bitrate" : 0,
      "duration" : 0,
      "title" : null,
      "properties" : null,
      "alternate" : null
    } ]
  }, {
    "href" : "https://raw.githubusercontent.com/duyhuynh652018/comic_storage9/main/IMAGE/IMAGE_32fd53686848c43580f2e351182d0ad8_0174d13e5dbeef7be19e7c3f7fa30fdd_fa32c75b9f7c4ac9961c194a3ee38b31.jpg",
    "type" : "image/jpeg",
    "bitrate" : 0,
    "duration" : 0,
    "title" : null,
    "properties" : null,
    "alternate" : [ {
      "href" : "https://i115.ntcdntempv3.com/data/images/9170/275777/023-fix.jpg?data=net",
      "type" : "image/jpeg",
      "bitrate" : 0,
      "duration" : 0,
      "title" : null,
      "properties" : null,
      "alternate" : null
    } ]
  }, {
    "href" : "https://raw.githubusercontent.com/duyhuynh652018/comic_storage9/main/IMAGE/IMAGE_32fd53686848c43580f2e351182d0ad8_0174d13e5dbeef7be19e7c3f7fa30fdd_11e0273ffc99866165cfcc4d6392e6f7.jpg",
    "type" : "image/jpeg",
    "bitrate" : 0,
    "duration" : 0,
    "title" : null,
    "properties" : null,
    "alternate" : [ {
      "href" : "https://i115.ntcdntempv3.com/data/images/9170/275777/024-fix.jpg?data=net",
      "type" : "image/jpeg",
      "bitrate" : 0,
      "duration" : 0,
      "title" : null,
      "properties" : null,
      "alternate" : null
    } ]
  } ],
  "toc" : null,
  "@context" : "https://readium.org/webpub-manifest/context.jsonld"
}