{
  "metadata" : {
    "identifier" : "https://thuviensach.vn/thien-long-bat-bo-phan-2-13615.html",
    "title" : "THIÊN LONG BÁT BỘ - PHẦN 2",
    "subtitle" : "N/A",
    "author" : {
      "name" : "Kim Dung",
      "sortAs" : ""
    },
    "narrator" : "N/A",
    "language" : "vi",
    "description" : "<p>Tiêu Phong, Bang chủ Cái Bang, một vị hảo hán đầu đội trời chân đạp đất tính tình hào sảng vô tư. Nhưng một ngày kia, ông khám phá ra thân thế của mình, từ đó bị mọi người trong võ lâm ghét bõ. Thật ra ông là ai? Hư Trúc, một vị tiểu hòa thượng chùa Thiếu Lâm, tính tình ngay thẳng ngốc nghếch. Trong một lần hạ sơn, anh đã được một vị kì nhân truyền thụ võ nghệ và trở thành một vị Cung chủ được mọi người kính trọng. Hơn thế nữa, anh ta còn cưới được một vị tuyệt sắc giai nhân. Liệu phái Thiếu Lâm sẽ sử trí ra sao với Hư Trúc? Đoàn Dự, tiểu vương gia nước Đại Lý, là người hiền lành rất ghét võ công. Trong cuộc đời, cậu đã gặp rất nhiều mỹ nhân và hầu như tất cả những người này đều yêu thương cậu. Những người mà cậu luôn theo đuổi thì đã có ý trung nhân. Một ngày kia, cậu phát hiện ra tất cả những cô gái đó đều là em của cậu. Vậy Đoàn thế tử sẽ ra sao?</p>",
    "publisher" : "N/A",
    "subject" : null,
    "modified" : null,
    "published" : "2023-06-22",
    "duration" : 0,
    "abridged" : false,
    "conformsTo" : null,
    "numberOfPages" : null,
    "readingProgression" : null,
    "belongsTo" : null,
    "presentation" : null,
    "@type" : "http://schema.org/Audiobook",
    "schema:license" : "https://creativecommons.org/publicdomain/zero/1.0/"
  },
  "links" : [ {
    "rel" : "self",
    "href" : "https://raw.githubusercontent.com/vietduyhuynh90s/book_storage_two9/main/EPUB/EPUB_c630b5723d7237ae1ad5cf9a80a9c023.json",
    "type" : "application/audiobook+json"
  }, {
    "rel" : "cover",
    "href" : "https://raw.githubusercontent.com/vietduyhuynh90s/book_storage_two9/main/IMAGE/IMAGE_c630b5723d7237ae1ad5cf9a80a9c023.jpg",
    "type" : "image/jpeg",
    "height" : 300,
    "width" : 300
  } ],
  "readingOrder" : [ {
    "href" : "https://thuviensach.vn/img/audio/13615-thien-long-bat-bo-phan-2-thuviensach.vn.mp3?t=0",
    "type" : "audio/mpeg",
    "bitrate" : 128,
    "duration" : 0,
    "title" : "00:00:00 Thiên Long Bát Bộ - Phần 34",
    "properties" : null,
    "alternate" : null
  }, {
    "href" : "https://thuviensach.vn/img/audio/13615-thien-long-bat-bo-phan-2-thuviensach.vn.mp3?t=3143",
    "type" : "audio/mpeg",
    "bitrate" : 128,
    "duration" : 0,
    "title" : "00:52:23 Thiên Long Bát Bộ - Phần 35",
    "properties" : null,
    "alternate" : null
  }, {
    "href" : "https://thuviensach.vn/img/audio/13615-thien-long-bat-bo-phan-2-thuviensach.vn.mp3?t=6403",
    "type" : "audio/mpeg",
    "bitrate" : 128,
    "duration" : 0,
    "title" : "01:46:43 Thiên Long Bát Bộ - Phần 36",
    "properties" : null,
    "alternate" : null
  }, {
    "href" : "https://thuviensach.vn/img/audio/13615-thien-long-bat-bo-phan-2-thuviensach.vn.mp3?t=9451",
    "type" : "audio/mpeg",
    "bitrate" : 128,
    "duration" : 0,
    "title" : "02:37:31 Thiên Long Bát Bộ - Phần 37",
    "properties" : null,
    "alternate" : null
  }, {
    "href" : "https://thuviensach.vn/img/audio/13615-thien-long-bat-bo-phan-2-thuviensach.vn.mp3?t=12545",
    "type" : "audio/mpeg",
    "bitrate" : 128,
    "duration" : 0,
    "title" : "03:29:05 Thiên Long Bát Bộ - Phần 38",
    "properties" : null,
    "alternate" : null
  }, {
    "href" : "https://thuviensach.vn/img/audio/13615-thien-long-bat-bo-phan-2-thuviensach.vn.mp3?t=14957",
    "type" : "audio/mpeg",
    "bitrate" : 128,
    "duration" : 0,
    "title" : "04:09:17 Thiên Long Bát Bộ - Phần 39",
    "properties" : null,
    "alternate" : null
  }, {
    "href" : "https://thuviensach.vn/img/audio/13615-thien-long-bat-bo-phan-2-thuviensach.vn.mp3?t=18104",
    "type" : "audio/mpeg",
    "bitrate" : 128,
    "duration" : 0,
    "title" : "05:01:44 Thiên Long Bát Bộ - Phần 40",
    "properties" : null,
    "alternate" : null
  }, {
    "href" : "https://thuviensach.vn/img/audio/13615-thien-long-bat-bo-phan-2-thuviensach.vn.mp3?t=21246",
    "type" : "audio/mpeg",
    "bitrate" : 128,
    "duration" : 0,
    "title" : "05:54:06 Thiên Long Bát Bộ - Phần 41",
    "properties" : null,
    "alternate" : null
  }, {
    "href" : "https://thuviensach.vn/img/audio/13615-thien-long-bat-bo-phan-2-thuviensach.vn.mp3?t=24435",
    "type" : "audio/mpeg",
    "bitrate" : 128,
    "duration" : 0,
    "title" : "06:47:15 Thiên Long Bát Bộ - Phần 42",
    "properties" : null,
    "alternate" : null
  }, {
    "href" : "https://thuviensach.vn/img/audio/13615-thien-long-bat-bo-phan-2-thuviensach.vn.mp3?t=27590",
    "type" : "audio/mpeg",
    "bitrate" : 128,
    "duration" : 0,
    "title" : "07:39:50 Thiên Long Bát Bộ - Phần 43",
    "properties" : null,
    "alternate" : null
  }, {
    "href" : "https://thuviensach.vn/img/audio/13615-thien-long-bat-bo-phan-2-thuviensach.vn.mp3?t=30654",
    "type" : "audio/mpeg",
    "bitrate" : 128,
    "duration" : 0,
    "title" : "08:30:54 Thiên Long Bát Bộ - Phần 44",
    "properties" : null,
    "alternate" : null
  }, {
    "href" : "https://thuviensach.vn/img/audio/13615-thien-long-bat-bo-phan-2-thuviensach.vn.mp3?t=33208",
    "type" : "audio/mpeg",
    "bitrate" : 128,
    "duration" : 0,
    "title" : "09:13:28 Thiên Long Bát Bộ - Phần 45",
    "properties" : null,
    "alternate" : null
  }, {
    "href" : "https://thuviensach.vn/img/audio/13615-thien-long-bat-bo-phan-2-thuviensach.vn.mp3?t=36511",
    "type" : "audio/mpeg",
    "bitrate" : 128,
    "duration" : 0,
    "title" : "10:08:31 Thiên Long Bát Bộ - Phần 46",
    "properties" : null,
    "alternate" : null
  }, {
    "href" : "https://thuviensach.vn/img/audio/13615-thien-long-bat-bo-phan-2-thuviensach.vn.mp3?t=39161",
    "type" : "audio/mpeg",
    "bitrate" : 128,
    "duration" : 0,
    "title" : "10:52:41 Thiên Long Bát Bộ - Phần 47",
    "properties" : null,
    "alternate" : null
  }, {
    "href" : "https://thuviensach.vn/img/audio/13615-thien-long-bat-bo-phan-2-thuviensach.vn.mp3?t=42358",
    "type" : "audio/mpeg",
    "bitrate" : 128,
    "duration" : 0,
    "title" : "11:45:58 Thiên Long Bát Bộ - Phần 48",
    "properties" : null,
    "alternate" : null
  }, {
    "href" : "https://thuviensach.vn/img/audio/13615-thien-long-bat-bo-phan-2-thuviensach.vn.mp3?t=45436",
    "type" : "audio/mpeg",
    "bitrate" : 128,
    "duration" : 0,
    "title" : "12:37:16 Thiên Long Bát Bộ - Phần 49",
    "properties" : null,
    "alternate" : null
  }, {
    "href" : "https://thuviensach.vn/img/audio/13615-thien-long-bat-bo-phan-2-thuviensach.vn.mp3?t=48724",
    "type" : "audio/mpeg",
    "bitrate" : 128,
    "duration" : 0,
    "title" : "13:32:04 Thiên Long Bát Bộ - Phần 50",
    "properties" : null,
    "alternate" : null
  }, {
    "href" : "https://thuviensach.vn/img/audio/13615-thien-long-bat-bo-phan-2-thuviensach.vn.mp3?t=51889",
    "type" : "audio/mpeg",
    "bitrate" : 128,
    "duration" : 0,
    "title" : "14:24:49 Thiên Long Bát Bộ - Phần 51",
    "properties" : null,
    "alternate" : null
  }, {
    "href" : "https://thuviensach.vn/img/audio/13615-thien-long-bat-bo-phan-2-thuviensach.vn.mp3?t=55269",
    "type" : "audio/mpeg",
    "bitrate" : 128,
    "duration" : 0,
    "title" : "15:21:09 Thiên Long Bát Bộ - Phần 52",
    "properties" : null,
    "alternate" : null
  }, {
    "href" : "https://thuviensach.vn/img/audio/13615-thien-long-bat-bo-phan-2-thuviensach.vn.mp3?t=58509",
    "type" : "audio/mpeg",
    "bitrate" : 128,
    "duration" : 0,
    "title" : "16:15:09 Thiên Long Bát Bộ - Phần 53",
    "properties" : null,
    "alternate" : null
  }, {
    "href" : "https://thuviensach.vn/img/audio/13615-thien-long-bat-bo-phan-2-thuviensach.vn.mp3?t=61715",
    "type" : "audio/mpeg",
    "bitrate" : 128,
    "duration" : 0,
    "title" : "17:08:35 Thiên Long Bát Bộ - Phần 54",
    "properties" : null,
    "alternate" : null
  }, {
    "href" : "https://thuviensach.vn/img/audio/13615-thien-long-bat-bo-phan-2-thuviensach.vn.mp3?t=64885",
    "type" : "audio/mpeg",
    "bitrate" : 128,
    "duration" : 0,
    "title" : "18:01:25 Thiên Long Bát Bộ - Phần 55",
    "properties" : null,
    "alternate" : null
  }, {
    "href" : "https://thuviensach.vn/img/audio/13615-thien-long-bat-bo-phan-2-thuviensach.vn.mp3?t=68151",
    "type" : "audio/mpeg",
    "bitrate" : 128,
    "duration" : 0,
    "title" : "18:55:51 Thiên Long Bát Bộ - Phần 56",
    "properties" : null,
    "alternate" : null
  }, {
    "href" : "https://thuviensach.vn/img/audio/13615-thien-long-bat-bo-phan-2-thuviensach.vn.mp3?t=71365",
    "type" : "audio/mpeg",
    "bitrate" : 128,
    "duration" : 0,
    "title" : "19:49:25 Thiên Long Bát Bộ - Phần 57",
    "properties" : null,
    "alternate" : null
  }, {
    "href" : "https://thuviensach.vn/img/audio/13615-thien-long-bat-bo-phan-2-thuviensach.vn.mp3?t=74530",
    "type" : "audio/mpeg",
    "bitrate" : 128,
    "duration" : 0,
    "title" : "20:42:10 Thiên Long Bát Bộ - Phần 58",
    "properties" : null,
    "alternate" : null
  }, {
    "href" : "https://thuviensach.vn/img/audio/13615-thien-long-bat-bo-phan-2-thuviensach.vn.mp3?t=77621",
    "type" : "audio/mpeg",
    "bitrate" : 128,
    "duration" : 0,
    "title" : "21:33:41 Thiên Long Bát Bộ - Phần 59",
    "properties" : null,
    "alternate" : null
  }, {
    "href" : "https://thuviensach.vn/img/audio/13615-thien-long-bat-bo-phan-2-thuviensach.vn.mp3?t=80849",
    "type" : "audio/mpeg",
    "bitrate" : 128,
    "duration" : 0,
    "title" : "22:27:29 Thiên Long Bát Bộ - Phần 60",
    "properties" : null,
    "alternate" : null
  }, {
    "href" : "https://thuviensach.vn/img/audio/13615-thien-long-bat-bo-phan-2-thuviensach.vn.mp3?t=84075",
    "type" : "audio/mpeg",
    "bitrate" : 128,
    "duration" : 0,
    "title" : "23:21:15 Thiên Long Bát Bộ - Phần 61",
    "properties" : null,
    "alternate" : null
  }, {
    "href" : "https://thuviensach.vn/img/audio/13615-thien-long-bat-bo-phan-2-thuviensach.vn.mp3?t=87318",
    "type" : "audio/mpeg",
    "bitrate" : 128,
    "duration" : 0,
    "title" : "24:15:18 Thiên Long Bát Bộ - Phần 62",
    "properties" : null,
    "alternate" : null
  }, {
    "href" : "https://thuviensach.vn/img/audio/13615-thien-long-bat-bo-phan-2-thuviensach.vn.mp3?t=90685",
    "type" : "audio/mpeg",
    "bitrate" : 128,
    "duration" : 0,
    "title" : "25:11:25 Thiên Long Bát Bộ - Phần 63",
    "properties" : null,
    "alternate" : null
  }, {
    "href" : "https://thuviensach.vn/img/audio/13615-thien-long-bat-bo-phan-2-thuviensach.vn.mp3?t=94090",
    "type" : "audio/mpeg",
    "bitrate" : 128,
    "duration" : 0,
    "title" : "26:08:10 Thiên Long Bát Bộ - Phần 64",
    "properties" : null,
    "alternate" : null
  }, {
    "href" : "https://thuviensach.vn/img/audio/13615-thien-long-bat-bo-phan-2-thuviensach.vn.mp3?t=97545",
    "type" : "audio/mpeg",
    "bitrate" : 128,
    "duration" : 0,
    "title" : "27:05:45 Thiên Long Bát Bộ - Phần 65",
    "properties" : null,
    "alternate" : null
  }, {
    "href" : "https://thuviensach.vn/img/audio/13615-thien-long-bat-bo-phan-2-thuviensach.vn.mp3?t=100911",
    "type" : "audio/mpeg",
    "bitrate" : 128,
    "duration" : 0,
    "title" : "28:01:51 Thiên Long Bát Bộ - Phần 66",
    "properties" : null,
    "alternate" : null
  } ],
  "toc" : [ {
    "href" : "https://thuviensach.vn/img/audio/13615-thien-long-bat-bo-phan-2-thuviensach.vn.mp3?t=0",
    "title" : "00:00:00 Thiên Long Bát Bộ - Phần 34",
    "children" : [ ]
  }, {
    "href" : "https://thuviensach.vn/img/audio/13615-thien-long-bat-bo-phan-2-thuviensach.vn.mp3?t=3143",
    "title" : "00:52:23 Thiên Long Bát Bộ - Phần 35",
    "children" : [ ]
  }, {
    "href" : "https://thuviensach.vn/img/audio/13615-thien-long-bat-bo-phan-2-thuviensach.vn.mp3?t=6403",
    "title" : "01:46:43 Thiên Long Bát Bộ - Phần 36",
    "children" : [ ]
  }, {
    "href" : "https://thuviensach.vn/img/audio/13615-thien-long-bat-bo-phan-2-thuviensach.vn.mp3?t=9451",
    "title" : "02:37:31 Thiên Long Bát Bộ - Phần 37",
    "children" : [ ]
  }, {
    "href" : "https://thuviensach.vn/img/audio/13615-thien-long-bat-bo-phan-2-thuviensach.vn.mp3?t=12545",
    "title" : "03:29:05 Thiên Long Bát Bộ - Phần 38",
    "children" : [ ]
  }, {
    "href" : "https://thuviensach.vn/img/audio/13615-thien-long-bat-bo-phan-2-thuviensach.vn.mp3?t=14957",
    "title" : "04:09:17 Thiên Long Bát Bộ - Phần 39",
    "children" : [ ]
  }, {
    "href" : "https://thuviensach.vn/img/audio/13615-thien-long-bat-bo-phan-2-thuviensach.vn.mp3?t=18104",
    "title" : "05:01:44 Thiên Long Bát Bộ - Phần 40",
    "children" : [ ]
  }, {
    "href" : "https://thuviensach.vn/img/audio/13615-thien-long-bat-bo-phan-2-thuviensach.vn.mp3?t=21246",
    "title" : "05:54:06 Thiên Long Bát Bộ - Phần 41",
    "children" : [ ]
  }, {
    "href" : "https://thuviensach.vn/img/audio/13615-thien-long-bat-bo-phan-2-thuviensach.vn.mp3?t=24435",
    "title" : "06:47:15 Thiên Long Bát Bộ - Phần 42",
    "children" : [ ]
  }, {
    "href" : "https://thuviensach.vn/img/audio/13615-thien-long-bat-bo-phan-2-thuviensach.vn.mp3?t=27590",
    "title" : "07:39:50 Thiên Long Bát Bộ - Phần 43",
    "children" : [ ]
  }, {
    "href" : "https://thuviensach.vn/img/audio/13615-thien-long-bat-bo-phan-2-thuviensach.vn.mp3?t=30654",
    "title" : "08:30:54 Thiên Long Bát Bộ - Phần 44",
    "children" : [ ]
  }, {
    "href" : "https://thuviensach.vn/img/audio/13615-thien-long-bat-bo-phan-2-thuviensach.vn.mp3?t=33208",
    "title" : "09:13:28 Thiên Long Bát Bộ - Phần 45",
    "children" : [ ]
  }, {
    "href" : "https://thuviensach.vn/img/audio/13615-thien-long-bat-bo-phan-2-thuviensach.vn.mp3?t=36511",
    "title" : "10:08:31 Thiên Long Bát Bộ - Phần 46",
    "children" : [ ]
  }, {
    "href" : "https://thuviensach.vn/img/audio/13615-thien-long-bat-bo-phan-2-thuviensach.vn.mp3?t=39161",
    "title" : "10:52:41 Thiên Long Bát Bộ - Phần 47",
    "children" : [ ]
  }, {
    "href" : "https://thuviensach.vn/img/audio/13615-thien-long-bat-bo-phan-2-thuviensach.vn.mp3?t=42358",
    "title" : "11:45:58 Thiên Long Bát Bộ - Phần 48",
    "children" : [ ]
  }, {
    "href" : "https://thuviensach.vn/img/audio/13615-thien-long-bat-bo-phan-2-thuviensach.vn.mp3?t=45436",
    "title" : "12:37:16 Thiên Long Bát Bộ - Phần 49",
    "children" : [ ]
  }, {
    "href" : "https://thuviensach.vn/img/audio/13615-thien-long-bat-bo-phan-2-thuviensach.vn.mp3?t=48724",
    "title" : "13:32:04 Thiên Long Bát Bộ - Phần 50",
    "children" : [ ]
  }, {
    "href" : "https://thuviensach.vn/img/audio/13615-thien-long-bat-bo-phan-2-thuviensach.vn.mp3?t=51889",
    "title" : "14:24:49 Thiên Long Bát Bộ - Phần 51",
    "children" : [ ]
  }, {
    "href" : "https://thuviensach.vn/img/audio/13615-thien-long-bat-bo-phan-2-thuviensach.vn.mp3?t=55269",
    "title" : "15:21:09 Thiên Long Bát Bộ - Phần 52",
    "children" : [ ]
  }, {
    "href" : "https://thuviensach.vn/img/audio/13615-thien-long-bat-bo-phan-2-thuviensach.vn.mp3?t=58509",
    "title" : "16:15:09 Thiên Long Bát Bộ - Phần 53",
    "children" : [ ]
  }, {
    "href" : "https://thuviensach.vn/img/audio/13615-thien-long-bat-bo-phan-2-thuviensach.vn.mp3?t=61715",
    "title" : "17:08:35 Thiên Long Bát Bộ - Phần 54",
    "children" : [ ]
  }, {
    "href" : "https://thuviensach.vn/img/audio/13615-thien-long-bat-bo-phan-2-thuviensach.vn.mp3?t=64885",
    "title" : "18:01:25 Thiên Long Bát Bộ - Phần 55",
    "children" : [ ]
  }, {
    "href" : "https://thuviensach.vn/img/audio/13615-thien-long-bat-bo-phan-2-thuviensach.vn.mp3?t=68151",
    "title" : "18:55:51 Thiên Long Bát Bộ - Phần 56",
    "children" : [ ]
  }, {
    "href" : "https://thuviensach.vn/img/audio/13615-thien-long-bat-bo-phan-2-thuviensach.vn.mp3?t=71365",
    "title" : "19:49:25 Thiên Long Bát Bộ - Phần 57",
    "children" : [ ]
  }, {
    "href" : "https://thuviensach.vn/img/audio/13615-thien-long-bat-bo-phan-2-thuviensach.vn.mp3?t=74530",
    "title" : "20:42:10 Thiên Long Bát Bộ - Phần 58",
    "children" : [ ]
  }, {
    "href" : "https://thuviensach.vn/img/audio/13615-thien-long-bat-bo-phan-2-thuviensach.vn.mp3?t=77621",
    "title" : "21:33:41 Thiên Long Bát Bộ - Phần 59",
    "children" : [ ]
  }, {
    "href" : "https://thuviensach.vn/img/audio/13615-thien-long-bat-bo-phan-2-thuviensach.vn.mp3?t=80849",
    "title" : "22:27:29 Thiên Long Bát Bộ - Phần 60",
    "children" : [ ]
  }, {
    "href" : "https://thuviensach.vn/img/audio/13615-thien-long-bat-bo-phan-2-thuviensach.vn.mp3?t=84075",
    "title" : "23:21:15 Thiên Long Bát Bộ - Phần 61",
    "children" : [ ]
  }, {
    "href" : "https://thuviensach.vn/img/audio/13615-thien-long-bat-bo-phan-2-thuviensach.vn.mp3?t=87318",
    "title" : "24:15:18 Thiên Long Bát Bộ - Phần 62",
    "children" : [ ]
  }, {
    "href" : "https://thuviensach.vn/img/audio/13615-thien-long-bat-bo-phan-2-thuviensach.vn.mp3?t=90685",
    "title" : "25:11:25 Thiên Long Bát Bộ - Phần 63",
    "children" : [ ]
  }, {
    "href" : "https://thuviensach.vn/img/audio/13615-thien-long-bat-bo-phan-2-thuviensach.vn.mp3?t=94090",
    "title" : "26:08:10 Thiên Long Bát Bộ - Phần 64",
    "children" : [ ]
  }, {
    "href" : "https://thuviensach.vn/img/audio/13615-thien-long-bat-bo-phan-2-thuviensach.vn.mp3?t=97545",
    "title" : "27:05:45 Thiên Long Bát Bộ - Phần 65",
    "children" : [ ]
  }, {
    "href" : "https://thuviensach.vn/img/audio/13615-thien-long-bat-bo-phan-2-thuviensach.vn.mp3?t=100911",
    "title" : "28:01:51 Thiên Long Bát Bộ - Phần 66",
    "children" : [ ]
  } ],
  "@context" : "https://readium.org/webpub-manifest/context.jsonld"
}